recval/__init__.py
recval/constants.py
recval/decorators.py
recval/evaluator.py
recval/metrics/__init__.py
recval/metrics/accuracy.py
recval/metrics/factory.py
recval/metrics/metric_interface.py
recval/metrics/metrics.py
recval/metrics/metrics_utils.py
recval/metrics/ranking.py
recval/utils.py
recval-0.1.2.dist-info/LICENSE
recval-0.1.2.dist-info/WHEEL
recval-0.1.2.dist-info/METADATA
recval-0.1.2.dist-info/RECORD
